{
  "data": [
    {
      "img": "images/artdiy_tsv5yi.png",
      "title": "등산"
    },
    {
      "img": "images/climbingtrekking_ji3hoz.png",
      "title": "심리 상담"
    },
    {
      "img": "images/cooking_o7lbqv.png",
      "title": "DIY"
    },
    {
      "img": "images/counseling_qvahhm.png",
      "title": "요리"
    },
    {
      "img": "images/jejutravel_sriln0.png",
      "title": "밀키트"
    },
    {
      "img": "images/mealkit_cabcmx (1).png",
      "title": "랜선클럽"
    },
    {
      "img": "images/onlineclub_yhjgfd.png",
      "title": "프립VOD"
    },
    {
      "img": "images/vod_nmfjxg.png",
      "title": "제주도"
    }
  ]
}
